[
      {
        "id": "1",
        "question":"How would you write a function in JS?",
        "image": "",
        "correct": 3,
        "answers": [
            {
              "id": "1",
              "answer": "def doSomething"
            },
            {
              "id": "2",
              "answer": "public function doSomething()"
            },
            {
              "id": "3",
              "answer": "funtion doSomething()"
            },
            {
              "id": "4",
              "answer": "public void doSomething()"
            }
          ]
      },
      {
          "id": "2",
          "question":"How do you add links in html?",
          "image": "",
          "correct": 3,
          "answers": [
              {
                  "id": "1",
                  "answer": "<div></div>"
              },
              {
                  "id": "2",
                  "answer": "You can't-read the docs!!"
              },
              {
                  "id": "3",
                  "answer": "<a href=' '></a>"
              },
              {
                  "id": "4",
                  "answer": "<link href=' '></link>"
              }
          ]
      },
      {
          "id": "3",
          "question": "what does css stand for?",
          "image": "",
          "correct": 3,
          "answers": [
              {
                  "id": "1",
                  "answer": "Computer Science Sheets"
              },
              {
                  "id": "2",
                  "answer": "Cascading Science Sheets"
              },
              {
                  "id": "3",
                  "answer": "Cascading Style Sheets"
              },
              {
                  "id": "4",
                  "answer": "Coding Style Sheets"
              }
          ]
      },
      {
          "id": "4",
          "image": "",
          "question": "corazvofdjsf?",
          "correct": 4,
          "answers": [
              {
                  "id": "1",
                  "answer": "@#@#@# "
              },
              {
                  "id": "2",
                  "answer": "/exec"
              },
              {
                  "id": "3",
                  "answer": "/#!!hfdjhfd"
              },
              {
                  "id": "4",
                  "answer": "You are trolling :)"
              }
          ]
      },
      {
          "id": "5",
          "image": "",
          "question": "What does CN stand for in CN tower?",
          "correct": 2,
          "answers": [
              {
                  "id": "1",
                  "answer": "Corporate National"
              },
              {
                  "id": "2",
                  "answer": "Canadain National"
              },
              {
                  "id": "3",
                  "answer": "Canadian Network"
              },
              {
                  "id": "4",
                  "answer": "Canadian Native"
              }
          ]
      },
      {
          "id": "6",
          "image": "",
          "question": "Which Canadian Province produces most oil?",
          "correct": 1,
          "answers": [
              {
                  "id": "1",
                  "answer": "Alberta"
              },
              {
                  "id": "2",
                  "answer": "Nothwest Territories"
              },
              {
                  "id": "3",
                  "answer": "Manitoba"
              },
              {
                  "id": "4",
                  "answer": "New Brunswick"
              }
          ]
      },
      {
          "id": "7",
          "image": "",
          "question": "Which city is refered as 'The City of Hundred Bell Towers'?",
          "correct": 2,
          "answers": [
              {
                  "id": "1",
                  "answer": "Vancouver"
              },
              {
                  "id": "2",
                  "answer": "Montreal"
              },
              {
                  "id": "3",
                  "answer": "Ottawa"
              },
              {
                  "id": "4",
                  "answer": "Edmonton"
              }
          ]
      }

]
